boundedcontours/__init__.py
boundedcontours/contour.py
boundedcontours/filter.py
boundedcontours/demo/__init__.py
boundedcontours/demo/distributions.py
boundedcontours/demo/mean_integrated_squared_error.py
boundedcontours/demo/utils.py
boundedcontours-0.0.3.dist-info/LICENSE
boundedcontours-0.0.3.dist-info/METADATA
boundedcontours-0.0.3.dist-info/WHEEL
boundedcontours-0.0.3.dist-info/top_level.txt
boundedcontours-0.0.3.dist-info/RECORD
